pygitloc/__init__.py
pygitloc/main.py
pygitloc-0.5.dist-info/METADATA
pygitloc-0.5.dist-info/WHEEL
pygitloc-0.5.dist-info/entry_points.txt
pygitloc-0.5.dist-info/top_level.txt
pygitloc-0.5.dist-info/RECORD
