Metadata-Version: 2.1
Name: pygitloc
Version: 0.5
Summary: A package to calculate lines of code from a GitHub repository link
Home-page: https://github.com/yourusername/pygitloc
Author: Shubham Shinde
Author-email: shubhamshindesunil@gmail.com
Classifier: Programming Language :: Python :: 3
Classifier: License :: OSI Approved :: MIT License
Classifier: Operating System :: OS Independent
Requires-Python: >=3.6
Requires-Dist: GitPython
Requires-Dist: PyGithub
